<TableData>
  <Description>Defines a thing.</Description>
  <DefaultEditorDescriptionColumn>universalCommand00</DefaultEditorDescriptionColumn>
  <Column>
	<Name>ID</Name>
	<ColumnType>ID</ColumnType>
  </Column>
  <Column>
	<Name>localizedTextIdNoArgToAll</Name>
	<ColumnType>LocalizedTextID</ColumnType>
  </Column>
  <Column>
	<Name>localizedTextIdNoArgToSelf</Name>
	<ColumnType>LocalizedTextID</ColumnType>
  </Column>
  <Column>
	<Name>localizedTextIdArgToAll</Name>
	<ColumnType>LocalizedTextID</ColumnType>
  </Column>
  <Column>
	<Name>localizedTextIdArgToArg</Name>
	<ColumnType>LocalizedTextID</ColumnType>
  </Column>
  <Column>
	<Name>localizedTextIdArgToSelf</Name>
	<ColumnType>LocalizedTextID</ColumnType>
  </Column>
  <Column>
	<Name>localizedTextIdSelfToAll</Name>
	<ColumnType>LocalizedTextID</ColumnType>
  </Column>
  <Column>
	<Name>localizedTextIdSelfToSelf</Name>
	<ColumnType>LocalizedTextID</ColumnType>
  </Column>
  <Column>
	<Name>localizedTextIdCommand</Name>
	<ColumnType>LocalizedTextID</ColumnType>
  </Column>
  <Column>
	<Name>localizedTextIdNotFoundToAll</Name>
	<ColumnType>LocalizedTextID</ColumnType>
  </Column>
  <Column>
	<Name>localizedTextIdNotFoundToSelf</Name>
	<ColumnType>LocalizedTextID</ColumnType>
  </Column>
  <Column>
	<Name>itemDisplayId</Name>
	<ColumnType>Reference</ColumnType>
	<RefTable>ItemDisplay</RefTable>
  </Column>
</TableData>
